MetodoParaFuncionesMultivariadas/__init__.py
MetodoParaFuncionesMultivariadas/MetodosDeGradiente/Gradiente_Conjugado.py
MetodoParaFuncionesMultivariadas/MetodosDeGradiente/Metodo_Cauchy.py
MetodoParaFuncionesMultivariadas/MetodosDeGradiente/Metodo_Fletcher_Reeves.py
MetodoParaFuncionesMultivariadas/MetodosDeGradiente/Metodo_Newton.py
MetodoParaFuncionesMultivariadas/MetodosDeGradiente/__init__.py
MetodoParaFuncionesMultivariadas/MetodosDirectos/Algoritmos_con_restricciones.py
MetodoParaFuncionesMultivariadas/MetodosDirectos/Algoritmos_sin_restricciones.py
MetodoParaFuncionesMultivariadas/MetodosDirectos/BusquedaUnidireccional.py
MetodoParaFuncionesMultivariadas/MetodosDirectos/__init__.py
MetodoParaFuncionesMultivariadas/MetodosDirectosMultivariadas/Caminata_Aleatoria.py
MetodoParaFuncionesMultivariadas/MetodosDirectosMultivariadas/Hooke_Jeeves.py
MetodoParaFuncionesMultivariadas/MetodosDirectosMultivariadas/Nelder_mead.py
MetodoParaFuncionesMultivariadas/MetodosDirectosMultivariadas/__init__.py
MetodosParaFuncionesDeUnaVariable/__init__.py
MetodosParaFuncionesDeUnaVariable/MetodosBasadosEnLaDerivada/Metodo_Biseccion.py
MetodosParaFuncionesDeUnaVariable/MetodosBasadosEnLaDerivada/Metodo_Newton_Raphson.py
MetodosParaFuncionesDeUnaVariable/MetodosBasadosEnLaDerivada/Metodo_Secante.py
MetodosParaFuncionesDeUnaVariable/MetodosBasadosEnLaDerivada/__init__.py
MetodosParaFuncionesDeUnaVariable/MetodosDeEliminacionDeRegiones/Busqueda_Fibonacci.py
MetodosParaFuncionesDeUnaVariable/MetodosDeEliminacionDeRegiones/Metodo_Division_Intervalos.py
MetodosParaFuncionesDeUnaVariable/MetodosDeEliminacionDeRegiones/Metodo_Seccion_Dorada.py
MetodosParaFuncionesDeUnaVariable/MetodosDeEliminacionDeRegiones/__init__.py
Parcial1/Ejercicio_Caja.py
Parcial1/Ejercicio_Cerca.py
Parcial1/Ejercicio_Lata.py
Parcial1/Ejercicio_Lata2.py
Parcial1/__init__.py
PaqueteOpt-0.0.1.dist-info/METADATA
PaqueteOpt-0.0.1.dist-info/WHEEL
PaqueteOpt-0.0.1.dist-info/top_level.txt
PaqueteOpt-0.0.1.dist-info/RECORD
